koco
