Metadata-Version: 2.1
Name: koco
Version: 0.2.3
Summary: A library to easily access kocohub datasets
Home-page: https://github.com/inmoonlight/koco
Author: Jihyung Moon
Author-email: mjihyung@gmail.com
License: MIT
Keywords: korean nlp datasets
Platform: UNKNOWN
Classifier: Programming Language :: Python :: 3
Classifier: Intended Audience :: Science/Research
